wraperr/__init__.py
wraperr/wrap_error.py
wraperr-1.0.2.dist-info/LICENSE
wraperr-1.0.2.dist-info/METADATA
wraperr-1.0.2.dist-info/WHEEL
wraperr-1.0.2.dist-info/top_level.txt
wraperr-1.0.2.dist-info/RECORD
