Metadata-Version: 2.1
Name: wraperr
Version: 1.0.2
Summary: Define exception handling logic via a decorator.
Author: Bálint Kókai
Author-email: galsaizoltan1@gmail.com
License: UNKNOWN
Platform: UNKNOWN
Requires-Python: >=2.7, !=3.0.*, !=3.1.*, !=3.2.*, !=3.3.*, !=3.4.*, <4
License-File: LICENSE
Provides-Extra: dev
